cvqp-0.2.2.dist-info/RECORD
cvqp-0.2.2.dist-info/WHEEL
cvqp-0.2.2.dist-info/top_level.txt
cvqp-0.2.2.dist-info/METADATA
cvqp-0.2.2.dist-info/licenses/LICENSE
cvqp/admm.py
cvqp/__init__.py
cvqp/types.py
cvqp/py.typed
cvqp/projection.py
cvqp/libs/proj_sum_largest.h
cvqp/libs/__init__.py
cvqp/libs/proj_sum_largest.cpython-313-darwin.so
cvqp/libs/proj_sum_largest.cpp
cvqp/libs/bindings.cpp
