Metadata-Version: 2.4
Name: cvqp
Version: 0.2.2
Summary: A Python implementation of the CVQP solver for CVaR-constrained quadratic programs
Author: David Pérez Piñeiro, Eric Luxenberg
License: Apache-2.0
Project-URL: Repository, https://github.com/cvxgrp/cvqp
Classifier: Development Status :: 4 - Beta
Classifier: Intended Audience :: Science/Research
Classifier: License :: OSI Approved :: Apache Software License
Classifier: Programming Language :: Python :: 3.8
Classifier: Programming Language :: Python :: 3.9
Classifier: Programming Language :: Python :: 3.10
Classifier: Programming Language :: Python :: 3.11
Classifier: Programming Language :: Python :: 3.12
Classifier: Topic :: Scientific/Engineering :: Mathematics
Classifier: Topic :: Scientific/Engineering :: Artificial Intelligence
Requires-Python: >=3.10
License-File: LICENSE
Requires-Dist: numpy>=1.20.0
Requires-Dist: scipy>=1.7.0
Provides-Extra: test
Requires-Dist: pytest>=8.3.5; extra == "test"
Requires-Dist: cvxpy>=1.6.0; extra == "test"
Provides-Extra: dev
Requires-Dist: ipykernel>=6.29.5; extra == "dev"
Requires-Dist: jupyter>=1.1.1; extra == "dev"
Requires-Dist: mosek>=10.2.8; python_version < "3.13" and extra == "dev"
Requires-Dist: pyinstrument>=5.0.0; extra == "dev"
Requires-Dist: pandas>=2.2.3; extra == "dev"
Requires-Dist: black>=24.10.0; extra == "dev"
Requires-Dist: line-profiler>=4.2.0; extra == "dev"
Requires-Dist: pytest>=8.3.5; extra == "dev"
Requires-Dist: pre-commit>=4.2.0; extra == "dev"
Requires-Dist: ruff>=0.12.0; extra == "dev"
Requires-Dist: tqdm>=4.67.1; extra == "dev"
Requires-Dist: cvxpy>=1.6.0; extra == "dev"
Requires-Dist: matplotlib>=3.9.2; extra == "dev"
Dynamic: license-file
